[{"name":"Finca Tamana Variedad Colombia","price":21.38,"cultivar":"Variedad Colombia","notes":"Sweet chocolate, caramel & red fruits","producer":"Elias Roa & Bellanid Sanchez","country":"Colombia","region":"El Pital, Huila","process":"Washed","harvest":"May – June 2024","roast":"light","size":250,"link":"https://timwendelboe.no/product/finca-tamana-colombian-filter-coffe-2/","roaster":{"name":"Tim Wendelboe","country":"no"},"id":"b5aaae90-46f8-4201-ac50-5f1bda8fec78"},{"name":"Nacimiento Pacas","price":20.11,"cultivar":"Pacas","notes":"Stone fruits, red berries & herbal","producer":"Jobneel Caceres Dios","country":"Honduras","region":"El Cielito, Santa Barbara","process":"Washed","harvest":"April 2024","roast":"light","size":250,"link":"https://timwendelboe.no/product/nacimiento-pacas/","roaster":{"name":"Tim Wendelboe","country":"no"},"id":"bb161610-4f3b-41f1-8748-ee0de0894701"},{"name":"Finca el Vikingo","price":25.5,"cultivar":"Geisha","notes":"Herbal, floral & citrus","producer":"Jobneel Caceres Dios","country":"Honduras","region":"El Sauce, Santa Barbara","process":"Washed","harvest":"May 2024","roast":"light","size":250,"link":"https://timwendelboe.no/product/finca-el-vikingo/","roaster":{"name":"Tim Wendelboe","country":"no"},"id":"bf9adc80-10a2-4a84-9635-251a21e3c8e0"},{"name":"Finca Tamana Caturron","price":22.56,"cultivar":"Caturron","notes":"Herbal, floral habanero & papaya","producer":"Elias Roa & Bellanid Sanchez","country":"Colombia","region":"El Pital, Huila","process":"Washed","harvest":"May – June 2024","roast":"light","size":250,"link":"https://timwendelboe.no/product/finca-tamana-caturron/","roaster":{"name":"Tim Wendelboe","country":"no"},"id":"c365d917-7a8a-40c4-9507-7238db0c54e8"},{"name":"Finca Tamana Castillo Espresso","price":21.38,"cultivar":"Castillo Tambo","notes":"Herbal, red fruits & dark chocolate","producer":"Elias Roa & Bellanid Sanchez","country":"Colombia","region":"El Pital, Huila","process":"Washed","harvest":"July 2024","roast":"espresso","size":250,"link":"https://timwendelboe.no/product/finca-tamana-castillo-espresso-2/","roaster":{"name":"Tim Wendelboe","country":"no"},"id":"7420bf2c-3d16-4482-9bb3-308ed3c764ed"},{"name":"Los Pirineos Pacamara Honey Processed","price":21.58,"cultivar":"Pacamara","notes":"Winey, stone fruits & cacao nibs","producer":"Diego Baraona","country":"El Salvador","region":"Tecapa-Chinameca, Usulutan","process":"Honey","harvest":"February 2024","roast":"light","size":250,"link":"https://timwendelboe.no/product/los-pirineos-pacamara-honey-processed/","roaster":{"name":"Tim Wendelboe","country":"no"},"id":"8f12f67c-598f-400c-a344-2050882cf5b4"},{"name":"Finca Tamana Bourbon","price":23.44,"cultivar":"Red & pink Bourbon (Ethiopian)","notes":"Winey, red fruits & floral","producer":"Elias Roa & Bellanid Sanchez","country":"Colombia","region":"El Pital, Huila","process":"Washed","harvest":"May 2024","roast":"light","size":250,"link":"https://timwendelboe.no/product/finca-tamana-bourbon/","roaster":{"name":"Tim Wendelboe","country":"no"},"id":"f9001195-914c-4308-b0e2-9fede928edf3"},{"name":"Finca Tamana Caturron Espresso","price":22.56,"cultivar":"Caturron","notes":"Herbal, floral habanero & papaya","producer":"Elias Roa & Bellanid Sanchez","country":"Colombia","region":"El Pital, Huila","process":"Washed","harvest":"May – June 2024","roast":"espresso","size":250,"link":"https://timwendelboe.no/product/finca-tamana-caturron-espresso/","roaster":{"name":"Tim Wendelboe","country":"no"},"id":"185bdb6f-01a1-4173-9df3-10e7e833eb7e"},{"name":"Danche","price":"25.00","cultivar":"Ethiopian Landrace","notes":"Earl grey tea, watermelon, and peach.\n","producer":"Danche","country":"Ethiopia","region":"Gedeb, Gedeo","process":"Washed","harvest":"December, 2024","roast":"light","size":250,"link":"https://www.seycoffee.com/collections/coffee/products/2025-danche-ethiopia","roaster":{"name":"Sey","country":"us"},"id":"591ef5fd-c513-43ea-b559-9c7e597d45b3"},{"name":"Daniel Caro Lopez","price":"24.75","cultivar":"Chiroso","notes":"Yellow tropical fruit, tamarind, and rose.\n","producer":"Daniel Caro Lopez","country":"Colombia","region":"Guintar, Anzá","process":"Washed","harvest":"January, 2025","roast":"light","size":250,"link":"https://www.seycoffee.com/collections/coffee/products/2025-daniel-caro-lopez-el-tambo-colombia","roaster":{"name":"Sey","country":"us"},"id":"574015b6-121a-41a6-8fa8-db0c4559face"},{"name":"Gerald Njagi","price":"25.50","cultivar":"SL28","notes":"Pomegranate, black currant, and hibiscus.\n","producer":"Gerald Njagi","country":"Kenya","region":"Kirinyaga","process":"Washed","harvest":"November, 2024","roast":"light","size":250,"link":"https://www.seycoffee.com/collections/coffee/products/2025-gerald-njagi-kambarare-kenya","roaster":{"name":"Sey","country":"us"},"id":"ec1c4a8e-23d8-4173-92ce-5bdcf9dc1337"},{"name":"Sike Bokossa","price":"25.00","cultivar":"Ethiopian Landrace","notes":"Watermelon, peach, and lemongrass.\n","producer":"Sike Bokossa","country":"Ethiopia","region":"Guji","process":"Washed","harvest":"December, 2024","roast":"light","size":250,"link":"https://www.seycoffee.com/collections/coffee/products/2025-sike-bokossa-ethiopia","roaster":{"name":"Sey","country":"us"},"id":"712f2bdb-d950-49bd-9014-18e35a3e9cfe"},{"name":"Jair Arles Galindez","price":"26.00","cultivar":"Pink Bourbon","notes":"Pomegranate, meyer lemon, and hibiscus.\n","producer":"Jair Arles Galindez","country":"Colombia","region":"Purutal, San Agustín, Huila","process":"Washed","harvest":"January, 2025","roast":"light","size":250,"link":"https://www.seycoffee.com/collections/coffee/products/2025-jair-arles-galindez-el-guayabo-2nd-harvest-colombia","roaster":{"name":"Sey","country":"us"},"id":"351d5072-1e14-4bc9-8eff-aea56bcbc045"},{"name":"Huila","price":"23.00","cultivar":"Caturra, V. Colombia, Castillo","notes":"Jam, dark chocolate, and lemon zest.\n","producer":"Huila","country":"Colombia","region":"Huila","process":"Washed","harvest":"July, 2024","roast":"light","size":250,"link":"https://www.seycoffee.com/collections/coffee/products/huila-decaffeinated","roaster":{"name":"Sey","country":"us"},"id":"846d772c-d61b-4506-9dd3-7408c89997c2"},{"name":"DECAF Espresso","price":22.46,"roast":"espresso","link":"https://www.langorakaffe.no/store/p/encanto1-p7dfr","cultivar":["Castillo","Colombia","Caturra"],"process":"Natural","notes":["Jammy","Baking spices","Caramel"],"producer":"Azahar Coffee","country":"Colombia","region":"Huila","altitude":[1400,2000],"harvest":null,"size":null,"roaster":{"name":"Langøra","country":"no"},"id":"08764061-1603-48c4-b014-6ff8ba4e5203"},{"name":"El Encanto #2","price":22.46,"roast":"light","link":"https://www.langorakaffe.no/store/p/encanto2","cultivar":"Castillo, Tabi, Colombia","process":"Extended Fermentation Natural","notes":"Raspberry, Port wine, Dark chocolate","producer":"Juan Saldarriaga","country":"Colombia","region":"Ciudad Bolivar, Antioquia","altitude":[1380,1800],"harvest":"September to January","size":null,"roaster":{"name":"Langøra","country":"no"},"id":"1cfd9f6b-9aab-4010-9061-762353f9cfdf"},{"name":"El Encanto #1","price":22.46,"roast":"light","link":"https://www.langorakaffe.no/store/p/encanto1","cultivar":"Castillo, Tabi","process":"Fully Washed","notes":"Stone fruit, nuts, vanilla","producer":"Juan Saldarriaga","country":"Colombia","region":"Ciudad Bolivar, Antioquia","altitude":[1380,1800],"harvest":"September to January","size":null,"roaster":{"name":"Langøra","country":"no"},"id":"4c7fffcc-dc5f-4255-aa7f-4890bf88580d"},{"name":"La Chiquita - Rum Barrel Aged","price":38.74,"roast":"light","link":"https://www.langorakaffe.no/store/p/la-chiquita-colombia","cultivar":"Tabi","process":"Rum Barrel Washed","notes":"Sweet, funky, dried fruit","producer":"Diego Bedoya","country":"Colombia","region":"Palestina, Caldas","altitude":[1600,1800],"harvest":null,"size":250,"roaster":{"name":"Langøra","country":"no"},"id":"55bc757d-dc0a-4372-9405-6874e5efeb68"},{"name":"✨ Monteblanco Geisha","price":38.74,"roast":"light","link":"https://www.langorakaffe.no/store/p/geisha","cultivar":"Geisha","process":"Washed","notes":"Lemongrass, jasmine, peach","producer":"Rodrigo Sanchez Valencia","country":"Colombia","region":"Acevedo, Huila","altitude":1550,"harvest":null,"size":250,"roaster":{"name":"Langøra","country":"no"},"id":"5aebe08d-9bc8-4462-b884-eac2c370a6cc"},{"name":"El Recreo","price":23.44,"roast":"light","link":"https://www.langorakaffe.no/store/p/recreo","cultivar":"Caturron","process":"Washed/Bærtørket (translated from Norwegian to:  Sun Dried)","notes":"Cherry, dark chocolate, pineapple","producer":"Alirio Rodriguez","country":"Colombia","region":"La Estrella, Acevedo, Huila","altitude":1550,"harvest":null,"size":null,"roaster":{"name":"Langøra","country":"no"},"id":"35f2859f-8f7a-49c9-b7b7-d51e2757317a"},{"name":"Gadio Siko","price":21.58,"roast":"light","link":"https://www.langorakaffe.no/store/p/gadio","cultivar":"Heirloom","process":"Berry dried","notes":"Blueberry, blackcurrant, black tea","producer":"Muluken Mamo","country":"Ethiopia","region":"Gedeb","altitude":[1950,2000],"harvest":null,"size":null,"roaster":{"name":"Langøra","country":"no"},"id":"afe50bdd-d83e-4e26-b1e1-a4f795446e3d"},{"name":"La Huaca","price":21.58,"roast":"light","link":"https://www.langorakaffe.no/store/p/peru","cultivar":"Caturra, Yellow Bourbon","process":"Washed","notes":"Apple, plum, milk chocolate","producer":"Origin Coffee Lab","country":"Peru","region":"Huabal, Jaén","altitude":null,"harvest":null,"size":10,"roaster":{"name":"Langøra","country":"no"},"id":"dc0f82da-ad4e-48fb-b51c-471f6a6b4bce"},{"name":"Trapiá","price":18.54,"roast":"light","link":"https://www.langorakaffe.no/store/p/brasil","cultivar":"Acaia","process":"Washed","notes":"Caramel, rose hip, stone fruit","producer":"Andrea Rangel & Renato Pita","country":"Brazil","region":"Mantiqueira de Minas","altitude":[1150,1400],"harvest":null,"size":250,"roaster":{"name":"Langøra","country":"no"},"id":"4abeacf3-b1d0-4a6e-95ed-6aaa9ac7d1b2"},{"name":"Trapiá Espresso","price":18.54,"roast":"espresso","link":"https://www.langorakaffe.no/store/p/brasil-es","cultivar":"Acaia","process":"Washed","notes":["Caramel","Rose hip","Stone fruit"],"producer":"Andrea Rangel & Renato Pita","country":"Brazil","region":"Mantiqueira de Minas","altitude":[1150,1400],"harvest":null,"size":250,"roaster":{"name":"Langøra","country":"no"},"id":"d1db2eeb-5cb6-47b3-8782-1e6e1a2c1edb"},{"name":"Rugori","price":23.44,"roast":"light","link":"https://www.langorakaffe.no/store/p/rugori","cultivar":"Bourbon","process":"Anaerobic Washed","notes":"Plum, peach, brown sugar","producer":"Gasharu Coffee","country":"Rwanda","region":"Macuba, Nyamasheke","altitude":[1610,2100],"harvest":null,"size":250,"roaster":{"name":"Langøra","country":"no"},"id":"b16e966a-1b1d-4361-8065-fa5f3fd35617"},{"name":"Intego","price":23.44,"roast":"light","link":"https://www.langorakaffe.no/store/p/intego","cultivar":"Bourbon","process":"Anaerobic, berry dried (60 hours)","notes":"Blueberry, kiwi, tropical fruit","producer":"Gasharu Coffee","country":"Rwanda","region":"Macuba, Nyamasheke","altitude":[1600,2100],"harvest":null,"size":250,"roaster":{"name":"Langøra","country":"no"},"id":"aaf34049-d886-47cd-8d41-c076fb7334c9"}]