[{"name":"Finca Tamana Variedad Colombia","price":21.59,"cultivar":"Variedad Colombia","notes":"Sweet chocolate, caramel & red fruits","producer":"Elias Roa & Bellanid Sanchez","country":"Colombia","region":"El Pital, Huila","process":"Washed","harvest":"May – June 2024","roast":"light","size":250,"link":"https://timwendelboe.no/product/finca-tamana-colombian-filter-coffe-2/","roaster":{"name":"Tim Wendelboe","country":"no"},"id":"4458d072-218f-4728-84a8-55d069ac3193"},{"name":"Nacimiento Pacas","price":20.3,"cultivar":"Pacas","notes":"Stone fruits, red berries & herbal","producer":"Jobneel Caceres Dios","country":"Honduras","region":"El Cielito, Santa Barbara","process":"Washed","harvest":"April 2024","roast":"light","size":250,"link":"https://timwendelboe.no/product/nacimiento-pacas/","roaster":{"name":"Tim Wendelboe","country":"no"},"id":"11ff3bb0-09b6-482f-8f59-a4570c558d82"},{"name":"Finca Tamana Caturron","price":22.77,"cultivar":"Caturron","notes":"Herbal, floral habanero & papaya","producer":"Elias Roa & Bellanid Sanchez","country":"Colombia","region":"El Pital, Huila","process":"Washed","harvest":"May – June 2024","roast":"light","size":250,"link":"https://timwendelboe.no/product/finca-tamana-caturron/","roaster":{"name":"Tim Wendelboe","country":"no"},"id":"174997d5-7d81-4e6f-8696-3ce8ecd8f04f"},{"name":"Finca Tamana Castillo Espresso","price":21.59,"cultivar":"Castillo Tambo","notes":"Herbal, red fruits & dark chocolate","producer":"Elias Roa & Bellanid Sanchez","country":"Colombia","region":"El Pital, Huila","process":"Washed","harvest":"July 2024","roast":"espresso","size":250,"link":"https://timwendelboe.no/product/finca-tamana-castillo-espresso-2/","roaster":{"name":"Tim Wendelboe","country":"no"},"id":"6723ee2e-d882-403b-8d52-3f81d99adc1b"},{"name":"Finca Tamana Bourbon","price":23.67,"cultivar":"Red & pink Bourbon (Ethiopian)","notes":"Winey, red fruits & floral","producer":"Elias Roa & Bellanid Sanchez","country":"Colombia","region":"El Pital, Huila","process":"Washed","harvest":"May 2024","roast":"light","size":250,"link":"https://timwendelboe.no/product/finca-tamana-bourbon/","roaster":{"name":"Tim Wendelboe","country":"no"},"id":"a9480011-adcf-4eec-bceb-f0c10b6d93a3"},{"name":"Finca Tamana SL28","price":23.67,"cultivar":"SL28","notes":"Red fruits, floral & chocolate","producer":"Elias Roa & Bellanid Sanchez","country":"Colombia","region":"El Pital, Huila","process":"Washed","harvest":"May – June 2024","roast":"light","size":250,"link":"https://timwendelboe.no/product/finca-tamana-sl28/","roaster":{"name":"Tim Wendelboe","country":"no"},"id":"9374ece9-a7cc-4cce-9ecb-b1b06b3daa9a"},{"name":"Marta & Jose Florez","price":"25.00","cultivar":"Chiroso","notes":"Gooseberry, and lemongrass.\n","producer":"Marta & Jose Florez","country":"Colombia","region":"Urrao, Antioquia","process":"Washed","harvest":"December, 2024","roast":"light","size":250,"link":"https://www.seycoffee.com/collections/coffee/products/2025-marta-jose-florez-el-silencio-colombia","roaster":{"name":"Sey","country":"us"},"id":"494b1cfd-3c48-4bbd-86d3-7e69111a4c74"},{"name":"Wilmer & Yenni Moncayo","price":"25.75","cultivar":"Pink Bourbon","notes":"Tropical fruit, floral oolong, and berry like sweetness.\n","producer":"Wilmer & Yenni Moncayo","country":"Colombia","region":"Pitalito, Huila","process":"Washed","harvest":"October, 2024","roast":"light","size":250,"link":"https://www.seycoffee.com/collections/coffee/products/2025-wilmer-yenni-moncayo-la-loma-colombia","roaster":{"name":"Sey","country":"us"},"id":"6f94327f-edb0-46c3-86c8-97eb2a062143"},{"name":"Danche","price":"25.00","cultivar":"Ethiopian Landrace","notes":"Earl grey tea, watermelon, and peach.\n","producer":"Danche","country":"Ethiopia","region":"Gedeb, Gedeo","process":"Washed","harvest":"December, 2024","roast":"light","size":250,"link":"https://www.seycoffee.com/collections/coffee/products/2025-danche-ethiopia","roaster":{"name":"Sey","country":"us"},"id":"0189fa78-41dc-44b9-b6a6-26f856139794"},{"name":"Gerald Njagi","price":"25.50","cultivar":"SL28","notes":"Pomegranate, black currant, and hibiscus.\n","producer":"Gerald Njagi","country":"Kenya","region":"Kirinyaga","process":"Washed","harvest":"November, 2024","roast":"light","size":250,"link":"https://www.seycoffee.com/collections/coffee/products/2025-gerald-njagi-kambarare-kenya","roaster":{"name":"Sey","country":"us"},"id":"207aa973-8ee3-41ef-8df7-a3ffde52cd10"},{"name":"Huila","price":"23.00","cultivar":"Caturra, V. Colombia, Castillo","notes":"Jam, dark chocolate, and lemon zest.\n","producer":"Huila","country":"Colombia","region":"Huila","process":"Washed","harvest":"July, 2024","roast":"light","size":250,"link":"https://www.seycoffee.com/collections/coffee/products/huila-decaffeinated","roaster":{"name":"Sey","country":"us"},"id":"614dab2f-a97b-41ad-a3c6-aa8663163b89"},{"name":"Miriam Quesada","price":23.67,"roast":"light","link":"https://www.langorakaffe.no/store/p/recreo-6gzdy","cultivar":"Pink Bourbon","process":"Washed","notes":"Passion fruit, cherry, black tea","producer":"Miriam Quesada & Librado Enciso","country":"Colombia","region":"Acevedo, Huila","altitude":1550,"harvest":null,"size":null,"roaster":{"name":"Langøra","country":"no"},"id":"99085ebd-3a68-4aa3-87c3-2a3d63d24604"},{"name":"DECAF Espresso","price":22.68,"roast":"espresso","link":"https://www.langorakaffe.no/store/p/encanto1-p7dfr","cultivar":["Castillo","Colombia","Caturra"],"process":"Natural","notes":["Jammy","Baking spices","Caramel"],"producer":"Azahar Coffee","country":"Colombia","region":"Huila","altitude":[1400,2000],"harvest":null,"size":null,"roaster":{"name":"Langøra","country":"no"},"id":"9af4eddf-475d-4d6e-9498-36b7840c558b"},{"name":"El Encanto #2","price":22.68,"roast":"light","link":"https://www.langorakaffe.no/store/p/encanto2","cultivar":"Castillo, Tabi, Colombia","process":"Extended Fermentation Natural","notes":"Raspberry, Port wine, Dark chocolate","producer":"Juan Saldarriaga","country":"Colombia","region":"Ciudad Bolivar, Antioquia","altitude":[1380,1800],"harvest":"September to January","size":null,"roaster":{"name":"Langøra","country":"no"},"id":"d538b53d-a556-493a-ad10-14b6a2cdb262"},{"name":"El Encanto #1","price":22.68,"roast":"light","link":"https://www.langorakaffe.no/store/p/encanto1","cultivar":"Castillo, Tabi","process":"Fully Washed","notes":"Stone fruit, nuts, vanilla","producer":"Juan Saldarriaga","country":"Colombia","region":"Ciudad Bolivar, Antioquia","altitude":[1380,1800],"harvest":"September to January","size":null,"roaster":{"name":"Langøra","country":"no"},"id":"744c3ec0-c8bb-477e-85b1-5008b0f4a365"},{"name":"✨ Monteblanco Geisha","price":39.11,"roast":"light","link":"https://www.langorakaffe.no/store/p/geisha","cultivar":"Geisha","process":"Washed","notes":"Lemongrass, jasmine, peach","producer":"Rodrigo Sanchez Valencia","country":"Colombia","region":"Acevedo, Huila","altitude":1550,"harvest":null,"size":250,"roaster":{"name":"Langøra","country":"no"},"id":"450e71f9-08fb-439e-9652-ff74f20f59a9"},{"name":"Trapiá","price":18.71,"roast":"light","link":"https://www.langorakaffe.no/store/p/brasil","cultivar":"Acaia","process":"Natural/Bærtørket (Dry)","notes":"Caramel, rosehip, stone fruit","producer":"Andrea Rangel & Renato Pita","country":"Brazil","region":"Mantiqueira de Minas","altitude":[1150,1400],"harvest":null,"size":250,"roaster":{"name":"Langøra","country":"no"},"id":"015d6523-e046-482b-8a67-3ae27e9073fd"},{"name":"Trapiá Espresso","price":18.71,"roast":"espresso","link":"https://www.langorakaffe.no/store/p/brasil-es","cultivar":"Acaia","process":"Natural/Dry","notes":["Caramel","Rosehip","Stone fruit"],"producer":"Andrea Rangel & Renato Pita","country":"Brazil","region":"Mantiqueira de Minas","altitude":[1150,1400],"harvest":null,"size":250,"roaster":{"name":"Langøra","country":"no"},"id":"8367f056-6380-4f12-9e62-e8e6aef33bb3"},{"name":"Rugori","price":23.67,"roast":"light","link":"https://www.langorakaffe.no/store/p/rugori","cultivar":"Bourbon","process":"Anaerobic Washed","notes":["Plum","Peach","Brown Sugar"],"producer":"Gasharu Coffee","country":"Rwanda","region":"Macuba, Nyamasheke","altitude":[1610,2100],"harvest":null,"size":250,"roaster":{"name":"Langøra","country":"no"},"id":"ab68c0a3-a028-4bbe-a828-c22b9b466475"},{"name":"Intego","price":23.67,"roast":"light","link":"https://www.langorakaffe.no/store/p/intego","cultivar":"Bourbon","process":"Anaerobic, Naturally Dried","notes":["Blueberry","Kiwi","Tropical Fruit"],"producer":"Gasharu Coffee","country":"Rwanda","region":"Macuba, Nyamasheke","altitude":[1600,2100],"harvest":null,"size":250,"roaster":{"name":"Langøra","country":"no"},"id":"17670656-e125-42b1-9b92-87ae8fd73bbd"}]